odoo/addons/mrp_packaging_default/README.rst
odoo/addons/mrp_packaging_default/__init__.py
odoo/addons/mrp_packaging_default/__manifest__.py
odoo/addons/mrp_packaging_default/i18n/es.po
odoo/addons/mrp_packaging_default/i18n/it.po
odoo/addons/mrp_packaging_default/i18n/mrp_packaging_default.pot
odoo/addons/mrp_packaging_default/models/__init__.py
odoo/addons/mrp_packaging_default/models/mrp_bom_line.py
odoo/addons/mrp_packaging_default/models/mrp_production.py
odoo/addons/mrp_packaging_default/models/stock_move.py
odoo/addons/mrp_packaging_default/readme/CONFIGURE.md
odoo/addons/mrp_packaging_default/readme/CONTEXT.md
odoo/addons/mrp_packaging_default/readme/CONTRIBUTORS.md
odoo/addons/mrp_packaging_default/readme/DESCRIPTION.md
odoo/addons/mrp_packaging_default/readme/USAGE.md
odoo/addons/mrp_packaging_default/static/description/icon.png
odoo/addons/mrp_packaging_default/static/description/index.html
odoo/addons/mrp_packaging_default/tests/__init__.py
odoo/addons/mrp_packaging_default/tests/test_mrp_packaging_default.py
odoo/addons/mrp_packaging_default/views/mrp_bom_view.xml
odoo/addons/mrp_packaging_default/views/mrp_production_view.xml
odoo_addon_mrp_packaging_default-18.0.1.0.0.3.dist-info/METADATA
odoo_addon_mrp_packaging_default-18.0.1.0.0.3.dist-info/WHEEL
odoo_addon_mrp_packaging_default-18.0.1.0.0.3.dist-info/top_level.txt
odoo_addon_mrp_packaging_default-18.0.1.0.0.3.dist-info/RECORD
