Metadata-Version: 2.1
Name: odoo-addon-mrp_packaging_default
Version: 18.0.1.0.0.3
Requires-Python: >=3.10
Requires-Dist: odoo-addon-stock_move_packaging_qty==18.0.*
Requires-Dist: odoo==18.0.*
Summary: Include packaging info in MRP by default
Home-page: https://github.com/OCA/manufacture
License: LGPL-3
Author: Moduon, Odoo Community Association (OCA)
Author-email: support@odoo-community.org
Classifier: Programming Language :: Python
Classifier: Framework :: Odoo
Classifier: Framework :: Odoo :: 18.0
Classifier: License :: OSI Approved :: GNU Lesser General Public License v3 (LGPLv3)
Classifier: Development Status :: 3 - Alpha
